cuequivariance_ops_cu11-0.5.1.dist-info/RECORD
cuequivariance_ops_cu11-0.5.1.dist-info/WHEEL
cuequivariance_ops_cu11-0.5.1.dist-info/METADATA
cuequivariance_ops_cu11-0.5.1.dist-info/licenses/LICENSE
cuequivariance_ops/__init__.py
cuequivariance_ops/VERSION
cuequivariance_ops/_version.py
cuequivariance_ops/lib/libcue_ops.so
cuequivariance_ops/equivariance/run_fmha_cudafree.h
cuequivariance_ops/equivariance/segmented_transpose.cuh
cuequivariance_ops/equivariance/run_fmha.h
cuequivariance_ops/equivariance/fused_tensor_product.cuh
cuequivariance_ops/equivariance/tensor_product_uniform_1d_jit.hh
cuequivariance_ops/equivariance/dtypes.hh
cuequivariance_ops/common/common.hpp
cuequivariance_ops/common/nvtx.hpp
cuequivariance_ops/triton/cache_manager.py
cuequivariance_ops/triton/__init__.py
cuequivariance_ops/triton/tuning_decorator.py
cuequivariance_ops/triton/fused_layer_norm_triton.py
cuequivariance_ops/triton/gated_gemm_triton.py
cuequivariance_ops/triton/cache/fused_sigmoid_gated_dual_gemm_backward_pregemm_kernel_wrapper.8.6.json
cuequivariance_ops/triton/cache/fused_sigmoid_gated_dual_gemm_backward_pregemm_kernel_wrapper.10.0.json
cuequivariance_ops/triton/cache/fused_sigmoid_gated_dual_gemm_forward_kernel_wrapper.8.0.json
cuequivariance_ops/triton/cache/fused_sigmoid_gated_dual_gemm_forward_kernel_wrapper.10.0.json
cuequivariance_ops/triton/cache/fused_sigmoid_gated_dual_gemm_backward_pregemm_kernel_wrapper.8.0.json
cuequivariance_ops/triton/cache/fused_sigmoid_gated_dual_gemm_backward_pregemm_kernel_wrapper.8.9.json
cuequivariance_ops/triton/cache/fused_sigmoid_gated_dual_gemm_backward_pregemm_kernel_wrapper.9.0.json
cuequivariance_ops/triton/cache/fused_sigmoid_gated_dual_gemm_forward_kernel_wrapper.8.6.json
cuequivariance_ops/triton/cache/fused_sigmoid_gated_dual_gemm_forward_kernel_wrapper.9.0.json
cuequivariance_ops/triton/cache/fused_sigmoid_gated_dual_gemm_forward_kernel_wrapper.8.9.json
