Metadata-Version: 2.1
Name: cuequivariance-ops-cu11
Version: 0.5.1
Summary: cuequivariance-ops - GPU Accelerated Extensions for Equivariant Primitives
Author: NVIDIA Corporation
License: # Software License Agreement
Classifier: Intended Audience :: Developers
Classifier: Programming Language :: Python
Project-URL: Homepage, https://github.com/nvidia/cuEquivariance
Project-URL: Documentation, https://github.com/nvidia/cuEquivariance
Requires-Python: >=3.10
Requires-Dist: tqdm
Requires-Dist: pynvml
Requires-Dist: platformdirs
Requires-Dist: numpy; extra == "test"
Requires-Dist: pytest; extra == "test"
Provides-Extra: test
